{"assets":[{"id":"suDYP8aRFNmLKK4qUpbbw","layers":[{"ddd":0,"ind":4,"ty":4,"nm":"","ln":"3384:39652","sr":1,"ks":{"a":{"a":0,"k":[0,0]},"o":{"a":0,"k":100},"p":{"a":0,"k":[840,800]},"r":{"a":0,"k":0},"s":{"a":0,"k":[100,100]},"sk":{"a":0,"k":0},"sa":{"a":0,"k":0}},"ao":0,"ip":0,"op":60,"st":0,"bm":0,"shapes":[{"ty":"gr","hd":false,"bm":0,"it":[{"ty":"el","hd":false,"p":{"a":0,"k":[0,0]},"s":{"a":0,"k":[32,56]},"d":1},{"ty":"fl","hd":false,"bm":0,"c":{"a":0,"k":[0.24,0.33,0.67]},"r":1,"o":{"a":0,"k":100}},{"ty":"tr","nm":"Transform","a":{"a":0,"k":[0,0]},"o":{"a":0,"k":100},"p":{"a":0,"k":[0,0]},"r":{"a":0,"k":0},"s":{"a":0,"k":[100,100]},"sk":{"a":0,"k":0},"sa":{"a":0,"k":0}}],"np":0}]},{"ddd":0,"ind":5,"ty":4,"nm":"","ln":"3384:39651","sr":1,"ks":{"a":{"a":0,"k":[0,0]},"o":{"a":0,"k":100},"p":{"a":0,"k":[760,800]},"r":{"a":0,"k":0},"s":{"a":0,"k":[100,100]},"sk":{"a":0,"k":0},"sa":{"a":0,"k":0}},"ao":0,"ip":0,"op":60,"st":0,"bm":0,"shapes":[{"ty":"gr","hd":false,"bm":0,"it":[{"ty":"el","hd":false,"p":{"a":0,"k":[0,0]},"s":{"a":0,"k":[32,56]},"d":1},{"ty":"fl","hd":false,"bm":0,"c":{"a":0,"k":[0.24,0.33,0.67]},"r":1,"o":{"a":0,"k":100}},{"ty":"tr","nm":"Transform","a":{"a":0,"k":[0,0]},"o":{"a":0,"k":100},"p":{"a":0,"k":[0,0]},"r":{"a":0,"k":0},"s":{"a":0,"k":[100,100]},"sk":{"a":0,"k":0},"sa":{"a":0,"k":0}}],"np":0}]}]},{"id":"Ur8lnc-n3YN3gha5vDITT","layers":[{"ddd":0,"ind":9,"ty":4,"nm":"","ln":"3384:39637","sr":1,"ks":{"a":{"a":0,"k":[0,0]},"o":{"a":0,"k":100},"p":{"a":0,"k":[840,800]},"r":{"a":0,"k":0},"s":{"a":0,"k":[100,100]},"sk":{"a":0,"k":0},"sa":{"a":0,"k":0}},"ao":0,"ip":0,"op":60,"st":0,"bm":0,"shapes":[{"ty":"gr","hd":false,"bm":0,"it":[{"ty":"el","hd":false,"p":{"a":0,"k":[0,0]},"s":{"a":0,"k":[32,56]},"d":1},{"ty":"fl","hd":false,"bm":0,"c":{"a":0,"k":[0.24,0.33,0.67]},"r":1,"o":{"a":0,"k":100}},{"ty":"tr","nm":"Transform","a":{"a":0,"k":[0,0]},"o":{"a":0,"k":100},"p":{"a":0,"k":[0,0]},"r":{"a":0,"k":0},"s":{"a":0,"k":[100,100]},"sk":{"a":0,"k":0},"sa":{"a":0,"k":0}}],"np":0}]},{"ddd":0,"ind":10,"ty":4,"nm":"","ln":"3384:39636","sr":1,"ks":{"a":{"a":0,"k":[0,0]},"o":{"a":0,"k":100},"p":{"a":0,"k":[760,800]},"r":{"a":0,"k":0},"s":{"a":0,"k":[100,100]},"sk":{"a":0,"k":0},"sa":{"a":0,"k":0}},"ao":0,"ip":0,"op":60,"st":0,"bm":0,"shapes":[{"ty":"gr","hd":false,"bm":0,"it":[{"ty":"el","hd":false,"p":{"a":0,"k":[0,0]},"s":{"a":0,"k":[32,56]},"d":1},{"ty":"fl","hd":false,"bm":0,"c":{"a":0,"k":[0.24,0.33,0.67]},"r":1,"o":{"a":0,"k":100}},{"ty":"tr","nm":"Transform","a":{"a":0,"k":[0,0]},"o":{"a":0,"k":100},"p":{"a":0,"k":[0,0]},"r":{"a":0,"k":0},"s":{"a":0,"k":[100,100]},"sk":{"a":0,"k":0},"sa":{"a":0,"k":0}}],"np":0}]}]},{"id":"Y6IUpbPl3NgnQbeykX2wf","layers":[{"ddd":0,"ind":11,"ty":4,"ln":"layer_11","sr":1,"ks":{"a":{"a":0,"k":[20.5,26]},"o":{"a":0,"k":100},"p":{"a":0,"k":[631.44,801]},"r":{"a":0,"k":0},"s":{"a":0,"k":[131.71,132.69]},"sk":{"a":0,"k":0},"sa":{"a":0,"k":0}},"ao":0,"ip":0,"op":60,"st":0,"bm":0,"shapes":[{"ty":"gr","nm":"surface121","it":[{"ty":"gr","it":[{"ty":"sh","d":1,"ks":{"a":0,"k":{"c":true,"i":[[0,0],[4.93,-9.4],[1.24,-1.62],[-1.09,0.24],[-5.29,-1.19],[-2.85,-3.09],[-2.36,-2.42],[0.7,2.77],[0.1,4.38],[-1.42,4.52],[-0.97,1.85],[-0.48,1.4],[0.37,0.03],[6.14,2.52],[3.47,2.39],[0.78,1.58]],"o":[[5.73,8.91],[-0.94,1.8],[-1.06,1.37],[5.27,-1.16],[4.32,0.97],[2.29,2.48],[1.48,1.52],[-1.07,-4.25],[-0.1,-4.58],[0.63,-1.99],[0.7,-1.33],[0.09,-0.27],[-6.66,-0.56],[-3.95,-1.62],[-1.44,-0.99],[0,0]],"v":[[8.05,6.97],[9.29,41.21],[6.69,46.81],[8.46,46.74],[25.66,46.45],[35.66,53.61],[42.47,61.07],[43.47,60.98],[41.83,47.98],[42.06,32.82],[44.7,26.76],[47.41,22.7],[41.48,22.51],[22.29,17.48],[11.83,10.89],[8.05,6.97]]}}},{"ty":"st","bm":0,"c":{"a":0,"k":[0.99,0.35,0.35,1]},"lc":2,"lj":2,"ml":4,"o":{"a":0,"k":100},"w":{"a":0,"k":12}},{"ty":"tr","nm":"Transform","a":{"a":0,"k":[0,0]},"o":{"a":0,"k":100},"p":{"a":0,"k":[0,0]},"r":{"a":0,"k":0},"s":{"a":0,"k":[75,75]},"sk":{"a":0,"k":0},"sa":{"a":0,"k":0}}]},{"ty":"tr","nm":"Transform","a":{"a":0,"k":[0,0]},"o":{"a":0,"k":100},"p":{"a":0,"k":[0,0]},"r":{"a":0,"k":0},"s":{"a":0,"k":[100,100]},"sk":{"a":0,"k":0},"sa":{"a":0,"k":0}}]}]},{"ddd":0,"ind":22,"ty":4,"ln":"layer_22","sr":1,"ks":{"a":{"a":0,"k":[23.5,8]},"o":{"a":0,"k":100},"p":{"a":0,"k":[970.44,789]},"r":{"a":0,"k":0},"s":{"a":0,"k":[131.91,131.25]},"sk":{"a":0,"k":0},"sa":{"a":0,"k":0}},"ao":0,"ip":0,"op":60,"st":0,"bm":0,"shapes":[{"ty":"gr","nm":"surface146","it":[{"ty":"gr","it":[{"ty":"sh","d":1,"ks":{"a":0,"k":{"c":false,"i":[[0,0],[-16.15,-1.83]],"o":[[15.83,3.71],[0,0]],"v":[[7,7],[55.13,14.92]]}}},{"ty":"st","bm":0,"c":{"a":0,"k":[0.99,0.35,0.35,1]},"lc":2,"lj":1,"ml":4,"o":{"a":0,"k":100},"w":{"a":0,"k":12}},{"ty":"tr","nm":"Transform","a":{"a":0,"k":[0,0]},"o":{"a":0,"k":100},"p":{"a":0,"k":[0,0]},"r":{"a":0,"k":0},"s":{"a":0,"k":[75,75]},"sk":{"a":0,"k":0},"sa":{"a":0,"k":0}}]},{"ty":"tr","nm":"Transform","a":{"a":0,"k":[0,0]},"o":{"a":0,"k":100},"p":{"a":0,"k":[0,0]},"r":{"a":0,"k":0},"s":{"a":0,"k":[100,100]},"sk":{"a":0,"k":0},"sa":{"a":0,"k":0}}]}]},{"ddd":0,"ind":14,"ty":4,"ln":"layer_14","sr":1,"ks":{"a":{"a":0,"k":[23.5,13]},"o":{"a":0,"k":100},"p":{"a":0,"k":[961.94,724]},"r":{"a":0,"k":0},"s":{"a":0,"k":[134.04,134.62]},"sk":{"a":0,"k":0},"sa":{"a":0,"k":0}},"ao":0,"ip":0,"op":60,"st":0,"bm":0,"shapes":[{"ty":"gr","nm":"surface126","it":[{"ty":"gr","it":[{"ty":"sh","d":1,"ks":{"a":0,"k":{"c":false,"i":[[0,0],[-9,3.52],[-7.84,2.14]],"o":[[7.45,-6.49],[7.57,-2.95],[0,0]],"v":[[6,28.71],[33.58,15.16],[56.66,7]]}}},{"ty":"st","bm":0,"c":{"a":0,"k":[0.99,0.35,0.35,1]},"lc":2,"lj":1,"ml":4,"o":{"a":0,"k":100},"w":{"a":0,"k":12}},{"ty":"tr","nm":"Transform","a":{"a":0,"k":[0,0]},"o":{"a":0,"k":100},"p":{"a":0,"k":[0,0]},"r":{"a":0,"k":0},"s":{"a":0,"k":[75,75]},"sk":{"a":0,"k":0},"sa":{"a":0,"k":0}}]},{"ty":"tr","nm":"Transform","a":{"a":0,"k":[0,0]},"o":{"a":0,"k":100},"p":{"a":0,"k":[0,0]},"r":{"a":0,"k":0},"s":{"a":0,"k":[100,100]},"sk":{"a":0,"k":0},"sa":{"a":0,"k":0}}]}]},{"ddd":0,"ind":13,"ty":4,"ln":"layer_13","sr":1,"ks":{"a":{"a":0,"k":[12,20.5]},"o":{"a":0,"k":100},"p":{"a":0,"k":[917.44,676.5]},"r":{"a":0,"k":0},"s":{"a":0,"k":[133.33,131.71]},"sk":{"a":0,"k":0},"sa":{"a":0,"k":0}},"ao":0,"ip":0,"op":60,"st":0,"bm":0,"shapes":[{"ty":"gr","nm":"surface246","it":[{"ty":"gr","it":[{"ty":"sh","d":1,"ks":{"a":0,"k":{"c":false,"i":[[0,0],[-7.32,13.17]],"o":[[8.33,-12.73],[0,0]],"v":[[6,47.53],[25.54,7]]}}},{"ty":"st","bm":0,"c":{"a":0,"k":[0.99,0.35,0.35,1]},"lc":2,"lj":1,"ml":4,"o":{"a":0,"k":100},"w":{"a":0,"k":12}},{"ty":"tr","nm":"Transform","a":{"a":0,"k":[0,0]},"o":{"a":0,"k":100},"p":{"a":0,"k":[0,0]},"r":{"a":0,"k":0},"s":{"a":0,"k":[75,75]},"sk":{"a":0,"k":0},"sa":{"a":0,"k":0}}]},{"ty":"tr","nm":"Transform","a":{"a":0,"k":[0,0]},"o":{"a":0,"k":100},"p":{"a":0,"k":[0,0]},"r":{"a":0,"k":0},"s":{"a":0,"k":[100,100]},"sk":{"a":0,"k":0},"sa":{"a":0,"k":0}}]}]},{"ddd":0,"ind":12,"ty":4,"ln":"layer_12","sr":1,"ks":{"a":{"a":0,"k":[7,7.5]},"o":{"a":0,"k":100},"p":{"a":0,"k":[687.94,713.5]},"r":{"a":0,"k":0},"s":{"a":0,"k":[135.71,133.33]},"sk":{"a":0,"k":0},"sa":{"a":0,"k":0}},"ao":0,"ip":0,"op":60,"st":0,"bm":0,"shapes":[{"ty":"gr","nm":"surface491","it":[{"ty":"gr","it":[{"ty":"sh","d":1,"ks":{"a":0,"k":{"c":false,"i":[[0,0],[-0.17,4.13],[6.38,-1.15]],"o":[[0.44,2.44],[0.23,-5.69],[0,0]],"v":[[7.14,7.94],[12.33,12.08],[6.89,6.52]]}}},{"ty":"st","bm":0,"c":{"a":0,"k":[0.99,0.35,0.35,1]},"lc":2,"lj":1,"ml":4,"o":{"a":0,"k":100},"w":{"a":0,"k":12}},{"ty":"tr","nm":"Transform","a":{"a":0,"k":[0,0]},"o":{"a":0,"k":100},"p":{"a":0,"k":[0,0]},"r":{"a":0,"k":0},"s":{"a":0,"k":[75,75]},"sk":{"a":0,"k":0},"sa":{"a":0,"k":0}}]},{"ty":"tr","nm":"Transform","a":{"a":0,"k":[0,0]},"o":{"a":0,"k":100},"p":{"a":0,"k":[0,0]},"r":{"a":0,"k":0},"s":{"a":0,"k":[100,100]},"sk":{"a":0,"k":0},"sa":{"a":0,"k":0}}]}]},{"ddd":0,"ind":15,"ty":4,"ln":"layer_15","sr":1,"ks":{"a":{"a":0,"k":[8,22.5]},"o":{"a":0,"k":100},"p":{"a":0,"k":[668.94,666.5]},"r":{"a":0,"k":0},"s":{"a":0,"k":[131.25,133.33]},"sk":{"a":0,"k":0},"sa":{"a":0,"k":0}},"ao":0,"ip":0,"op":60,"st":0,"bm":0,"shapes":[{"ty":"gr","nm":"surface496","it":[{"ty":"gr","it":[{"ty":"sh","d":1,"ks":{"a":0,"k":{"c":false,"i":[[0,0],[0,0]],"o":[[0,0],[0,0]],"v":[[6.04,6],[14.64,53.9]]}}},{"ty":"st","bm":0,"c":{"a":0,"k":[0.99,0.35,0.35,1]},"lc":2,"lj":1,"ml":4,"o":{"a":0,"k":100},"w":{"a":0,"k":12}},{"ty":"tr","nm":"Transform","a":{"a":0,"k":[0,0]},"o":{"a":0,"k":100},"p":{"a":0,"k":[0,0]},"r":{"a":0,"k":0},"s":{"a":0,"k":[75,75]},"sk":{"a":0,"k":0},"sa":{"a":0,"k":0}}]},{"ty":"tr","nm":"Transform","a":{"a":0,"k":[0,0]},"o":{"a":0,"k":100},"p":{"a":0,"k":[0,0]},"r":{"a":0,"k":0},"s":{"a":0,"k":[100,100]},"sk":{"a":0,"k":0},"sa":{"a":0,"k":0}}]}]},{"ddd":0,"ind":16,"ty":4,"ln":"layer_16","sr":1,"ks":{"a":{"a":0,"k":[7,7.5]},"o":{"a":0,"k":100},"p":{"a":0,"k":[670.94,740.5]},"r":{"a":0,"k":0},"s":{"a":0,"k":[135.71,133.33]},"sk":{"a":0,"k":0},"sa":{"a":0,"k":0}},"ao":0,"ip":0,"op":60,"st":0,"bm":0,"shapes":[{"ty":"gr","nm":"surface501","it":[{"ty":"gr","it":[{"ty":"sh","d":1,"ks":{"a":0,"k":{"c":false,"i":[[0,0],[-0.57,-0.9],[-0.21,1.24],[3.89,-0.7]],"o":[[-1.61,2.32],[0.47,0.74],[0.53,-3.09],[0,0]],"v":[[7.3,8.35],[8.56,11.65],[12.09,12.72],[8.87,6.76]]}}},{"ty":"st","bm":0,"c":{"a":0,"k":[0.99,0.35,0.35,1]},"lc":2,"lj":1,"ml":4,"o":{"a":0,"k":100},"w":{"a":0,"k":12}},{"ty":"tr","nm":"Transform","a":{"a":0,"k":[0,0]},"o":{"a":0,"k":100},"p":{"a":0,"k":[0,0]},"r":{"a":0,"k":0},"s":{"a":0,"k":[75,75]},"sk":{"a":0,"k":0},"sa":{"a":0,"k":0}}]},{"ty":"tr","nm":"Transform","a":{"a":0,"k":[0,0]},"o":{"a":0,"k":100},"p":{"a":0,"k":[0,0]},"r":{"a":0,"k":0},"s":{"a":0,"k":[100,100]},"sk":{"a":0,"k":0},"sa":{"a":0,"k":0}}]}]},{"ddd":0,"ind":17,"ty":4,"ln":"layer_17","sr":1,"ks":{"a":{"a":0,"k":[12,27]},"o":{"a":0,"k":100},"p":{"a":0,"k":[647.44,686.5]},"r":{"a":0,"k":0},"s":{"a":0,"k":[133.33,133.33]},"sk":{"a":0,"k":0},"sa":{"a":0,"k":0}},"ao":0,"ip":0,"op":60,"st":0,"bm":0,"shapes":[{"ty":"gr","nm":"surface506","it":[{"ty":"gr","it":[{"ty":"sh","d":1,"ks":{"a":0,"k":{"c":false,"i":[[0,0],[-4.75,-13.46],[-1.86,-5.97]],"o":[[2.83,13.98],[2.08,5.91],[0,0]],"v":[[7,6.16],[18.54,47.66],[25.6,65.05]]}}},{"ty":"st","bm":0,"c":{"a":0,"k":[0.99,0.35,0.35,1]},"lc":2,"lj":1,"ml":4,"o":{"a":0,"k":100},"w":{"a":0,"k":12}},{"ty":"tr","nm":"Transform","a":{"a":0,"k":[0,0]},"o":{"a":0,"k":100},"p":{"a":0,"k":[0,0]},"r":{"a":0,"k":0},"s":{"a":0,"k":[75,75]},"sk":{"a":0,"k":0},"sa":{"a":0,"k":0}}]},{"ty":"tr","nm":"Transform","a":{"a":0,"k":[0,0]},"o":{"a":0,"k":100},"p":{"a":0,"k":[0,0]},"r":{"a":0,"k":0},"s":{"a":0,"k":[100,100]},"sk":{"a":0,"k":0},"sa":{"a":0,"k":0}}]}]},{"ddd":0,"ind":2,"ty":4,"nm":"","ln":"3384:39653","sr":1,"ks":{"a":{"a":0,"k":[0,0]},"o":{"a":0,"k":100},"p":{"a":0,"k":[800.44,884]},"r":{"a":0,"k":0},"s":{"a":0,"k":[100,100]},"sk":{"a":0,"k":0},"sa":{"a":0,"k":0}},"ao":0,"ip":0,"op":60,"st":0,"bm":0,"shapes":[{"ty":"gr","hd":false,"bm":0,"it":[{"ty":"el","hd":false,"p":{"a":0,"k":[0,0]},"s":{"a":0,"k":[70,93]},"d":1},{"ty":"st","hd":false,"bm":0,"c":{"a":0,"k":[0.24,0.33,0.67]},"lc":2,"lj":1,"o":{"a":0,"k":100},"w":{"a":0,"k":12}},{"ty":"tr","nm":"Transform","a":{"a":0,"k":[0,0]},"o":{"a":0,"k":100},"p":{"a":0,"k":[0,0]},"r":{"a":0,"k":0},"s":{"a":0,"k":[100,100]},"sk":{"a":0,"k":0},"sa":{"a":0,"k":0}}],"np":0}]},{"ddd":0,"ind":3,"ty":0,"nm":"","ln":"precomp_3384:396503","sr":1,"ks":{"a":{"a":0,"k":[800,800]},"o":{"a":0,"k":100},"p":{"a":0,"k":[800.44,781.5]},"r":{"a":0,"k":0},"s":{"a":0,"k":[100,100]},"sk":{"a":0,"k":0},"sa":{"a":0,"k":0}},"ao":0,"w":1600,"h":1600,"ip":0,"op":60,"st":0,"bm":0,"refId":"suDYP8aRFNmLKK4qUpbbw"},{"ddd":0,"ind":19,"ty":4,"ln":"layer_19","sr":1,"ks":{"a":{"a":0,"k":[135,117]},"o":{"a":0,"k":100},"p":{"a":0,"k":[800.44,801.5]},"r":{"a":0,"k":0},"s":{"a":0,"k":[133.33,133.33]},"sk":{"a":0,"k":0},"sa":{"a":0,"k":0}},"ao":0,"ip":0,"op":60,"st":0,"bm":0,"shapes":[{"ty":"gr","nm":"surface511","it":[{"ty":"gr","it":[{"ty":"sh","d":1,"ks":{"a":0,"k":{"c":true,"i":[[0,0],[0,0],[0.01,-4.52],[-2.23,-3.92],[-3.89,-2.29],[-4.51,-0.05],[0,0],[-3.89,2.29],[-2.23,3.92],[0.01,4.51],[2.25,3.91],[0,0],[3.87,2.18],[4.44,0],[3.87,-2.18],[2.3,-3.8]],"o":[[0,0],[-2.26,3.91],[-0.01,4.51],[2.23,3.92],[3.89,2.29],[0,0],[4.51,-0.05],[3.89,-2.29],[2.23,-3.92],[-0.01,-4.52],[0,0],[-2.3,-3.8],[-3.87,-2.18],[-4.44,0],[-3.87,2.18],[0,0]],"v":[[112.91,12.45],[3.46,195.22],[0,208.08],[3.39,220.95],[12.74,230.43],[25.56,234],[244.44,234],[257.26,230.43],[266.61,220.95],[270,208.08],[266.54,195.22],[157.09,12.45],[147.68,3.32],[135,0],[122.32,3.32],[112.91,12.45]]}}},{"ty":"fl","c":{"a":0,"k":[0.99,0.35,0.35,1]},"r":1,"o":{"a":0,"k":100}},{"ty":"tr","nm":"Transform","a":{"a":0,"k":[0,0]},"o":{"a":0,"k":100},"p":{"a":0,"k":[0,0]},"r":{"a":0,"k":0},"s":{"a":0,"k":[100,100]},"sk":{"a":0,"k":0},"sa":{"a":0,"k":0}}]},{"ty":"tr","nm":"Transform","a":{"a":0,"k":[0,0]},"o":{"a":0,"k":100},"p":{"a":0,"k":[0,0]},"r":{"a":0,"k":0},"s":{"a":0,"k":[100,100]},"sk":{"a":0,"k":0},"sa":{"a":0,"k":0}}]}]}]},{"id":"cGlNXcfCrwBWsWgtYCGZm","layers":[{"ddd":0,"ind":18,"ty":4,"ln":"layer_18","sr":1,"ks":{"a":{"a":0,"k":[19,25]},"o":{"a":0,"k":100},"p":{"a":0,"k":[632.75,816]},"r":{"a":0,"k":0},"s":{"a":0,"k":[134.21,132]},"sk":{"a":0,"k":0},"sa":{"a":0,"k":0}},"ao":0,"ip":0,"op":60,"st":0,"bm":0,"shapes":[{"ty":"gr","nm":"surface131","it":[{"ty":"gr","it":[{"ty":"sh","d":1,"ks":{"a":0,"k":{"c":true,"i":[[0,0],[5.41,-7.7],[1.28,-1.28],[-0.98,0.08],[-4.48,-1.69],[-2.12,-3.07],[-1.77,-2.42],[0.28,2.53],[-0.43,3.88],[-1.78,3.81],[-1.07,1.52],[-0.58,1.17],[0.32,0.07],[5.06,2.96],[2.75,2.53],[0.5,1.48]],"o":[[3.95,8.55],[-1.04,1.47],[-1.08,1.08],[4.73,-0.39],[3.65,1.38],[1.7,2.46],[1.11,1.52],[-0.43,-3.87],[0.46,-4.06],[0.79,-1.68],[0.77,-1.09],[0.12,-0.23],[-5.74,-1.3],[-3.26,-1.9],[-1.14,-1.05],[0,0]],"v":[[12.26,6.26],[9.29,36.63],[6.35,41.26],[7.91,41.41],[22.95,43.22],[30.84,50.73],[35.9,58.14],[36.78,58.17],[36.89,46.51],[38.89,33.16],[41.92,28.11],[44.76,24.86],[39.6,23.98],[23.45,17.24],[15.1,10.17],[12.26,6.26]]}}},{"ty":"st","bm":0,"c":{"a":0,"k":[0.99,0.35,0.35,1]},"lc":2,"lj":2,"ml":4,"o":{"a":0,"k":100},"w":{"a":0,"k":12}},{"ty":"tr","nm":"Transform","a":{"a":0,"k":[0,0]},"o":{"a":0,"k":100},"p":{"a":0,"k":[0,0]},"r":{"a":0,"k":0},"s":{"a":0,"k":[75,75]},"sk":{"a":0,"k":0},"sa":{"a":0,"k":0}}]},{"ty":"tr","nm":"Transform","a":{"a":0,"k":[0,0]},"o":{"a":0,"k":100},"p":{"a":0,"k":[0,0]},"r":{"a":0,"k":0},"s":{"a":0,"k":[100,100]},"sk":{"a":0,"k":0},"sa":{"a":0,"k":0}}]}]},{"ddd":0,"ind":20,"ty":4,"ln":"layer_20","sr":1,"ks":{"a":{"a":0,"k":[23,8]},"o":{"a":0,"k":100},"p":{"a":0,"k":[962.75,772.5]},"r":{"a":0,"k":0},"s":{"a":0,"k":[132.61,131.25]},"sk":{"a":0,"k":0},"sa":{"a":0,"k":0}},"ao":0,"ip":0,"op":60,"st":0,"bm":0,"shapes":[{"ty":"gr","nm":"surface136","it":[{"ty":"gr","it":[{"ty":"sh","d":1,"ks":{"a":0,"k":{"c":false,"i":[[0,0],[-16.15,-1.83]],"o":[[15.83,3.71],[0,0]],"v":[[6.37,6.72],[54.5,14.64]]}}},{"ty":"st","bm":0,"c":{"a":0,"k":[0.99,0.35,0.35,1]},"lc":2,"lj":1,"ml":4,"o":{"a":0,"k":100},"w":{"a":0,"k":12}},{"ty":"tr","nm":"Transform","a":{"a":0,"k":[0,0]},"o":{"a":0,"k":100},"p":{"a":0,"k":[0,0]},"r":{"a":0,"k":0},"s":{"a":0,"k":[75,75]},"sk":{"a":0,"k":0},"sa":{"a":0,"k":0}}]},{"ty":"tr","nm":"Transform","a":{"a":0,"k":[0,0]},"o":{"a":0,"k":100},"p":{"a":0,"k":[0,0]},"r":{"a":0,"k":0},"s":{"a":0,"k":[100,100]},"sk":{"a":0,"k":0},"sa":{"a":0,"k":0}}]}]},{"ddd":0,"ind":21,"ty":4,"ln":"layer_21","sr":1,"ks":{"a":{"a":0,"k":[24,13]},"o":{"a":0,"k":100},"p":{"a":0,"k":[945.25,720.5]},"r":{"a":0,"k":0},"s":{"a":0,"k":[133.33,134.62]},"sk":{"a":0,"k":0},"sa":{"a":0,"k":0}},"ao":0,"ip":0,"op":60,"st":0,"bm":0,"shapes":[{"ty":"gr","nm":"surface141","it":[{"ty":"gr","it":[{"ty":"sh","d":1,"ks":{"a":0,"k":{"c":false,"i":[[0,0],[-9,3.52],[-7.84,2.14]],"o":[[7.45,-6.49],[7.57,-2.95],[0,0]],"v":[[6.55,28.08],[34.14,14.53],[57.21,6.37]]}}},{"ty":"st","bm":0,"c":{"a":0,"k":[0.99,0.35,0.35,1]},"lc":2,"lj":1,"ml":4,"o":{"a":0,"k":100},"w":{"a":0,"k":12}},{"ty":"tr","nm":"Transform","a":{"a":0,"k":[0,0]},"o":{"a":0,"k":100},"p":{"a":0,"k":[0,0]},"r":{"a":0,"k":0},"s":{"a":0,"k":[75,75]},"sk":{"a":0,"k":0},"sa":{"a":0,"k":0}}]},{"ty":"tr","nm":"Transform","a":{"a":0,"k":[0,0]},"o":{"a":0,"k":100},"p":{"a":0,"k":[0,0]},"r":{"a":0,"k":0},"s":{"a":0,"k":[100,100]},"sk":{"a":0,"k":0},"sa":{"a":0,"k":0}}]}]},{"ddd":0,"ind":23,"ty":4,"ln":"layer_23","sr":1,"ks":{"a":{"a":0,"k":[12,20]},"o":{"a":0,"k":100},"p":{"a":0,"k":[907.25,683.5]},"r":{"a":0,"k":0},"s":{"a":0,"k":[133.33,132.5]},"sk":{"a":0,"k":0},"sa":{"a":0,"k":0}},"ao":0,"ip":0,"op":60,"st":0,"bm":0,"shapes":[{"ty":"gr","nm":"surface151","it":[{"ty":"gr","it":[{"ty":"sh","d":1,"ks":{"a":0,"k":{"c":false,"i":[[0,0],[-7.31,13.17]],"o":[[8.33,-12.73],[0,0]],"v":[[6.12,46.58],[25.66,6.05]]}}},{"ty":"st","bm":0,"c":{"a":0,"k":[0.99,0.35,0.35,1]},"lc":2,"lj":1,"ml":4,"o":{"a":0,"k":100},"w":{"a":0,"k":12}},{"ty":"tr","nm":"Transform","a":{"a":0,"k":[0,0]},"o":{"a":0,"k":100},"p":{"a":0,"k":[0,0]},"r":{"a":0,"k":0},"s":{"a":0,"k":[75,75]},"sk":{"a":0,"k":0},"sa":{"a":0,"k":0}}]},{"ty":"tr","nm":"Transform","a":{"a":0,"k":[0,0]},"o":{"a":0,"k":100},"p":{"a":0,"k":[0,0]},"r":{"a":0,"k":0},"s":{"a":0,"k":[100,100]},"sk":{"a":0,"k":0},"sa":{"a":0,"k":0}}]}]},{"ddd":0,"ind":24,"ty":4,"ln":"layer_24","sr":1,"ks":{"a":{"a":0,"k":[7,7.5]},"o":{"a":0,"k":100},"p":{"a":0,"k":[688.25,720]},"r":{"a":0,"k":0},"s":{"a":0,"k":[128.57,133.33]},"sk":{"a":0,"k":0},"sa":{"a":0,"k":0}},"ao":0,"ip":0,"op":60,"st":0,"bm":0,"shapes":[{"ty":"gr","nm":"surface516","it":[{"ty":"gr","it":[{"ty":"sh","d":1,"ks":{"a":0,"k":{"c":false,"i":[[0,0],[-0.9,4.04],[6.48,0]],"o":[[0,2.48],[1.23,-5.56],[0,0]],"v":[[6.33,7.58],[10.71,12.58],[6.33,6.14]]}}},{"ty":"st","bm":0,"c":{"a":0,"k":[0.99,0.35,0.35,1]},"lc":2,"lj":1,"ml":4,"o":{"a":0,"k":100},"w":{"a":0,"k":12}},{"ty":"tr","nm":"Transform","a":{"a":0,"k":[0,0]},"o":{"a":0,"k":100},"p":{"a":0,"k":[0,0]},"r":{"a":0,"k":0},"s":{"a":0,"k":[75,75]},"sk":{"a":0,"k":0},"sa":{"a":0,"k":0}}]},{"ty":"tr","nm":"Transform","a":{"a":0,"k":[0,0]},"o":{"a":0,"k":100},"p":{"a":0,"k":[0,0]},"r":{"a":0,"k":0},"s":{"a":0,"k":[100,100]},"sk":{"a":0,"k":0},"sa":{"a":0,"k":0}}]}]},{"ddd":0,"ind":25,"ty":4,"ln":"layer_25","sr":1,"ks":{"a":{"a":0,"k":[5,23]},"o":{"a":0,"k":100},"p":{"a":0,"k":[676.75,670.5]},"r":{"a":0,"k":0},"s":{"a":0,"k":[130,132.61]},"sk":{"a":0,"k":0},"sa":{"a":0,"k":0}},"ao":0,"ip":0,"op":60,"st":0,"bm":0,"shapes":[{"ty":"gr","nm":"surface251","it":[{"ty":"gr","it":[{"ty":"sh","d":1,"ks":{"a":0,"k":{"c":false,"i":[[0,0],[0,0]],"o":[[0,0],[0,0]],"v":[[6.74,6],[6.74,54.67]]}}},{"ty":"st","bm":0,"c":{"a":0,"k":[0.99,0.35,0.35,1]},"lc":2,"lj":1,"ml":4,"o":{"a":0,"k":100},"w":{"a":0,"k":12}},{"ty":"tr","nm":"Transform","a":{"a":0,"k":[0,0]},"o":{"a":0,"k":100},"p":{"a":0,"k":[0,0]},"r":{"a":0,"k":0},"s":{"a":0,"k":[75,75]},"sk":{"a":0,"k":0},"sa":{"a":0,"k":0}}]},{"ty":"tr","nm":"Transform","a":{"a":0,"k":[0,0]},"o":{"a":0,"k":100},"p":{"a":0,"k":[0,0]},"r":{"a":0,"k":0},"s":{"a":0,"k":[100,100]},"sk":{"a":0,"k":0},"sa":{"a":0,"k":0}}]}]},{"ddd":0,"ind":27,"ty":4,"ln":"layer_27","sr":1,"ks":{"a":{"a":0,"k":[7,7.5]},"o":{"a":0,"k":100},"p":{"a":0,"k":[666.25,744]},"r":{"a":0,"k":0},"s":{"a":0,"k":[128.57,133.33]},"sk":{"a":0,"k":0},"sa":{"a":0,"k":0}},"ao":0,"ip":0,"op":60,"st":0,"bm":0,"shapes":[{"ty":"gr","nm":"surface521","it":[{"ty":"gr","it":[{"ty":"sh","d":1,"ks":{"a":0,"k":{"c":false,"i":[[0,0],[-0.4,-0.98],[-0.43,1.18],[3.95,0]],"o":[[-2,2],[0.33,0.82],[1.06,-2.95],[0,0]],"v":[[6.92,7.58],[7.57,11.05],[10.86,12.73],[8.74,6.3]]}}},{"ty":"st","bm":0,"c":{"a":0,"k":[0.99,0.35,0.35,1]},"lc":2,"lj":1,"ml":4,"o":{"a":0,"k":100},"w":{"a":0,"k":12}},{"ty":"tr","nm":"Transform","a":{"a":0,"k":[0,0]},"o":{"a":0,"k":100},"p":{"a":0,"k":[0,0]},"r":{"a":0,"k":0},"s":{"a":0,"k":[75,75]},"sk":{"a":0,"k":0},"sa":{"a":0,"k":0}}]},{"ty":"tr","nm":"Transform","a":{"a":0,"k":[0,0]},"o":{"a":0,"k":100},"p":{"a":0,"k":[0,0]},"r":{"a":0,"k":0},"s":{"a":0,"k":[100,100]},"sk":{"a":0,"k":0},"sa":{"a":0,"k":0}}]}]},{"ddd":0,"ind":26,"ty":4,"ln":"layer_26","sr":1,"ks":{"a":{"a":0,"k":[8,28]},"o":{"a":0,"k":100},"p":{"a":0,"k":[652.75,686]},"r":{"a":0,"k":0},"s":{"a":0,"k":[131.25,132.14]},"sk":{"a":0,"k":0},"sa":{"a":0,"k":0}},"ao":0,"ip":0,"op":60,"st":0,"bm":0,"shapes":[{"ty":"gr","nm":"surface256","it":[{"ty":"gr","it":[{"ty":"sh","d":1,"ks":{"a":0,"k":{"c":false,"i":[[0,0],[-2.3,-14.08],[-0.78,-6.21]],"o":[[0.32,14.27],[1.01,6.19],[0,0]],"v":[[6.61,6.33],[10.64,49.21],[14.52,67.58]]}}},{"ty":"st","bm":0,"c":{"a":0,"k":[0.99,0.35,0.35,1]},"lc":2,"lj":1,"ml":4,"o":{"a":0,"k":100},"w":{"a":0,"k":12}},{"ty":"tr","nm":"Transform","a":{"a":0,"k":[0,0]},"o":{"a":0,"k":100},"p":{"a":0,"k":[0,0]},"r":{"a":0,"k":0},"s":{"a":0,"k":[75,75]},"sk":{"a":0,"k":0},"sa":{"a":0,"k":0}}]},{"ty":"tr","nm":"Transform","a":{"a":0,"k":[0,0]},"o":{"a":0,"k":100},"p":{"a":0,"k":[0,0]},"r":{"a":0,"k":0},"s":{"a":0,"k":[100,100]},"sk":{"a":0,"k":0},"sa":{"a":0,"k":0}}]}]},{"ddd":0,"ind":7,"ty":4,"nm":"","ln":"3384:39638","sr":1,"ks":{"a":{"a":0,"k":[0,0]},"o":{"a":0,"k":100},"p":{"a":0,"k":[800.17,879.58]},"r":{"a":0,"k":0},"s":{"a":0,"k":[100,100]},"sk":{"a":0,"k":0},"sa":{"a":0,"k":0}},"ao":0,"ip":0,"op":60,"st":0,"bm":0,"shapes":[{"ty":"gr","hd":false,"bm":0,"it":[{"ty":"el","hd":false,"p":{"a":0,"k":[0,0]},"s":{"a":0,"k":[48,64]},"d":1},{"ty":"st","hd":false,"bm":0,"c":{"a":0,"k":[0.24,0.33,0.67]},"lc":2,"lj":1,"o":{"a":0,"k":100},"w":{"a":0,"k":12}},{"ty":"tr","nm":"Transform","a":{"a":0,"k":[0,0]},"o":{"a":0,"k":100},"p":{"a":0,"k":[0,0]},"r":{"a":0,"k":0},"s":{"a":0,"k":[100,100]},"sk":{"a":0,"k":0},"sa":{"a":0,"k":0}}],"np":0}]},{"ddd":0,"ind":8,"ty":0,"nm":"","ln":"precomp_3384:396358","sr":1,"ks":{"a":{"a":0,"k":[800,800]},"o":{"a":0,"k":100},"p":{"a":0,"k":[800.17,791.58]},"r":{"a":0,"k":0},"s":{"a":0,"k":[100,100]},"sk":{"a":0,"k":0},"sa":{"a":0,"k":0}},"ao":0,"w":1600,"h":1600,"ip":0,"op":60,"st":0,"bm":0,"refId":"Ur8lnc-n3YN3gha5vDITT"},{"ddd":0,"ind":28,"ty":4,"ln":"layer_28","sr":1,"ks":{"a":{"a":0,"k":[131.5,113.5]},"o":{"a":0,"k":100},"p":{"a":0,"k":[800.25,803.5]},"r":{"a":0,"k":0},"s":{"a":0,"k":[133.08,133.48]},"sk":{"a":0,"k":0},"sa":{"a":0,"k":0}},"ao":0,"ip":0,"op":60,"st":0,"bm":0,"shapes":[{"ty":"gr","nm":"surface261","it":[{"ty":"gr","it":[{"ty":"sh","d":1,"ks":{"a":0,"k":{"c":true,"i":[[0,0],[0,0],[0.02,-4.37],[-2.16,-3.79],[-3.76,-2.21],[-4.36,-0.05],[0,0],[-3.76,2.21],[-2.16,3.79],[0.01,4.36],[2.18,3.78],[0,0],[3.74,2.11],[4.3,0],[3.75,-2.11],[2.23,-3.67]],"o":[[0,0],[-2.18,3.78],[-0.01,4.36],[2.16,3.79],[3.76,2.21],[0,0],[4.37,-0.05],[3.76,-2.21],[2.16,-3.79],[-0.01,-4.37],[0,0],[-2.23,-3.67],[-3.75,-2.11],[-4.3,0],[-3.74,2.11],[0,0]],"v":[[109.81,12.25],[3.94,189],[0.59,201.43],[3.87,213.88],[12.91,223.05],[25.31,226.5],[237.06,226.5],[249.46,223.05],[258.51,213.88],[261.79,201.43],[258.44,189],[152.56,12.25],[143.45,3.43],[131.19,0.22],[118.92,3.43],[109.81,12.25]]}}},{"ty":"fl","c":{"a":0,"k":[0.99,0.35,0.35,1]},"r":1,"o":{"a":0,"k":100}},{"ty":"tr","nm":"Transform","a":{"a":0,"k":[0,0]},"o":{"a":0,"k":100},"p":{"a":0,"k":[0,0]},"r":{"a":0,"k":0},"s":{"a":0,"k":[100,100]},"sk":{"a":0,"k":0},"sa":{"a":0,"k":0}}]},{"ty":"tr","nm":"Transform","a":{"a":0,"k":[0,0]},"o":{"a":0,"k":100},"p":{"a":0,"k":[0,0]},"r":{"a":0,"k":0},"s":{"a":0,"k":[100,100]},"sk":{"a":0,"k":0},"sa":{"a":0,"k":0}}]}]}]}],"ddd":0,"fr":60,"h":400,"ip":0,"layers":[{"ddd":0,"ind":1,"ty":0,"nm":"","ln":"precomp_3384:396481","sr":1,"ks":{"a":{"a":0,"k":[800,800]},"o":{"a":1,"k":[{"t":0,"s":[100],"i":{"x":0,"y":0},"o":{"x":1,"y":1}},{"t":1,"s":[83.33],"i":{"x":0,"y":0},"o":{"x":1,"y":1}},{"t":2,"s":[66.67],"i":{"x":0,"y":0},"o":{"x":1,"y":1}},{"t":3,"s":[50],"i":{"x":0,"y":0},"o":{"x":1,"y":1}},{"t":4,"s":[33.33],"i":{"x":0,"y":0},"o":{"x":1,"y":1}},{"t":5,"s":[16.67],"i":{"x":0,"y":0},"o":{"x":1,"y":1}},{"t":6,"s":[0],"i":{"x":0,"y":0},"o":{"x":1,"y":1}},{"t":30,"s":[0],"i":{"x":0,"y":0},"o":{"x":1,"y":1}},{"t":31,"s":[16.67],"i":{"x":0,"y":0},"o":{"x":1,"y":1}},{"t":32,"s":[33.33],"i":{"x":0,"y":0},"o":{"x":1,"y":1}},{"t":33,"s":[50],"i":{"x":0,"y":0},"o":{"x":1,"y":1}},{"t":34,"s":[66.67],"i":{"x":0,"y":0},"o":{"x":1,"y":1}},{"t":35,"s":[83.33],"i":{"x":0,"y":0},"o":{"x":1,"y":1}},{"t":36,"s":[100],"i":{"x":0,"y":0},"o":{"x":1,"y":1}}]},"p":{"a":0,"k":[199.57,191.4]},"r":{"a":0,"k":0},"s":{"a":0,"k":[100,100]},"sk":{"a":0,"k":0},"sa":{"a":0,"k":0}},"ao":0,"w":1600,"h":1600,"ip":0,"op":60,"st":0,"bm":0,"refId":"Y6IUpbPl3NgnQbeykX2wf"},{"ddd":0,"ind":6,"ty":0,"nm":"","ln":"precomp_3384:396476","sr":1,"ks":{"a":{"a":0,"k":[800,800]},"o":{"a":1,"k":[{"t":0,"s":[100],"i":{"x":0,"y":0},"o":{"x":1,"y":1}},{"t":30,"s":[100],"i":{"x":0,"y":0},"o":{"x":1,"y":1}},{"t":31,"s":[83.33],"i":{"x":0,"y":0},"o":{"x":1,"y":1}},{"t":32,"s":[66.67],"i":{"x":0,"y":0},"o":{"x":1,"y":1}},{"t":33,"s":[50],"i":{"x":0,"y":0},"o":{"x":1,"y":1}},{"t":34,"s":[33.33],"i":{"x":0,"y":0},"o":{"x":1,"y":1}},{"t":35,"s":[16.67],"i":{"x":0,"y":0},"o":{"x":1,"y":1}},{"t":36,"s":[0],"i":{"x":0,"y":0},"o":{"x":1,"y":1}}]},"p":{"a":0,"k":[199.83,196]},"r":{"a":0,"k":0},"s":{"a":0,"k":[100,100]},"sk":{"a":0,"k":0},"sa":{"a":0,"k":0}},"ao":0,"w":1600,"h":1600,"ip":0,"op":60,"st":0,"bm":0,"refId":"cGlNXcfCrwBWsWgtYCGZm"}],"meta":{"g":"https://jitter.video"},"nm":"[ACT-HAND]-School-governance:-Component-1376","op":60,"v":"5.7.4","w":400}