{
 "smis_id": 10012014,
 "obec_id": 720044,
 "name_th": "โรงเรียนมัธยมวัดมกุฏกษัตริย์",
 "name_en": "Mattayom Wat Makutkasat School",
 "address": "หมู่ที่ บ้าน",
 "subdistrict": "บางขุนพรหม",
 "district": "เขตพระนคร",
 "province": "กรุงเทพมหานคร",
 "postcode": "10200",
 "telephone": "22813535",
 "fax": "22829493",
 "grades": "มัธยมศึกษาตอนต้น-มัธยมศึกษาตอนปลาย",
 "established": "7/6/2494",
 "email": "admin@makut.ac.th",
 "url_text_0": "เว็บไซต์โรงเรียน (สารสนเทศ)",
 "url_0": "https://data.bopp-obec.info/emis/../web/?School_ID=1010720044",
 "website": "www.makut.ac.th เว็บไซต์โรงเรียน (สารสนเทศ)",
 "network_of_education_development_center": null,
 "local_gov_org": "พระนคร",
 "distance_to_edu_area": "15 กม.",
 "distance_to_district": "2 กม.",
 "logo_image_path": "https://data.bopp-obec.info/emis/pic_school/1010720044.jpg",
 "principal_image_path": "https://data.bopp-obec.info/emis/pic/1010720116-20130813-130421.jpg",
 "latlng": "13.7650426667,100.507472927",
 "buildings": [
  {
   "name": "อาคารเรียน ลำดับที่ 1 ",
   "model": "พิเศษ 6 ชั้น",
   "room_number": "28 ห้อง",
   "build_at": "พ.ศ. 2538",
   "current_condition": "พอใช้",
   "image_url_0": "https://bobec.bopp-obec.info/b01/7200441014425380120211018163145328147282.jpg",
   "image_url_1": "https://bobec.bopp-obec.info/b01/7200441014425380120211018163155601114672.jpg"
  },
  {
   "name": "อาคารเรียน ลำดับที่ 2 ",
   "model": "พิเศษ 4 ชั้น",
   "room_number": "28 ห้อง",
   "build_at": "พ.ศ. 2496",
   "current_condition": "ทรุดโทรม",
   "image_url_0": "https://bobec.bopp-obec.info/b01/7200442014224960120211018163108529021911.jpg",
   "image_url_1": "https://bobec.bopp-obec.info/b01/7200442014224960120211018163114662894858.jpg"
  },
  {
   "name": "อาคารเรียน ลำดับที่ 3 ",
   "model": "พิเศษ 3 ชั้น",
   "room_number": "15 ห้อง",
   "build_at": "พ.ศ. 2529",
   "current_condition": "ทรุดโทรม",
   "image_url_0": "https://bobec.bopp-obec.info/b01/720044301412529012021101816301526001311.jpg",
   "image_url_1": "https://bobec.bopp-obec.info/b01/7200443014125290120211018163026506036146.jpg"
  },
  {
   "name": "อาคารเรียน ลำดับที่ 4 ",
   "model": "พิเศษ 4 ชั้น",
   "room_number": "8 ห้อง",
   "build_at": "พ.ศ. 2532",
   "current_condition": "ดี",
   "image_url_0": "https://bobec.bopp-obec.info/b01/7200444014225320120211018162820493721964.jpg",
   "image_url_1": "https://bobec.bopp-obec.info/b01/7200444014225320120211018162828909199925.jpg"
  },
  {
   "name": "อาคารเรียน ลำดับที่ 5 ",
   "model": "พิเศษ 5 ชั้น",
   "room_number": "41 ห้อง",
   "build_at": "พ.ศ. 2557",
   "current_condition": "ดี",
   "image_url_0": "https://bobec.bopp-obec.info/b01/10012014501432557201012021101816325474284787.jpg",
   "image_url_1": "https://bobec.bopp-obec.info/b01/100120145014325572010120211018163302930405448.jpg"
  }
 ],
 "computer": {
  "working": 241,
  "broken": 0,
  "total": 241,
  "learning": {
   "working": 161,
   "broken": 0,
   "total": 161,
   "source": {
    "obec": 31,
    "self": 130
   }
  },
  "management": {
   "working": 80,
   "broken": 0,
   "total": 80,
   "source": {
    "obec": 0,
    "self": 80
   }
  }
 },
 "durable_goods": [
  {
   "code": 11001,
   "type": "ครุภัณฑ์การศึกษา",
   "name": "โต๊ะเก้าอี้นักเรียนก่อนประถมศึกษา",
   "working": 0,
   "to_be_repaired": 0,
   "to_be_removed": 0,
   "total": 0
  },
  {
   "code": 11002,
   "type": "ครุภัณฑ์การศึกษา",
   "name": "ชุดฝึกทักษะนักเรียนก่อนประถมศึกษา",
   "working": 0,
   "to_be_repaired": 0,
   "to_be_removed": 0,
   "total": 0
  },
  {
   "code": 11003,
   "type": "ครุภัณฑ์การศึกษา",
   "name": "ตู้เก็บอุปกรณ์นักเรียนก่อนประถมศึกษา",
   "working": 0,
   "to_be_repaired": 0,
   "to_be_removed": 0,
   "total": 0
  },
  {
   "code": 21001,
   "type": "ครุภัณฑ์สำนักงาน โรงเรียน",
   "name": "เครื่องถ่ายเอกสาร",
   "working": 6,
   "to_be_repaired": 0,
   "to_be_removed": 0,
   "total": 6
  },
  {
   "code": 21002,
   "type": "ครุภัณฑ์สำนักงาน โรงเรียน",
   "name": "เครื่องพิมพ์สำเนาระบบดิจิตอล",
   "working": 2,
   "to_be_repaired": 0,
   "to_be_removed": 0,
   "total": 2
  },
  {
   "code": 21003,
   "type": "ครุภัณฑ์สำนักงาน โรงเรียน",
   "name": "เครื่องโทรสาร",
   "working": 3,
   "to_be_repaired": 0,
   "to_be_removed": 0,
   "total": 3
  },
  {
   "code": 21004,
   "type": "ครุภัณฑ์สำนักงาน โรงเรียน",
   "name": "เครื่องอัดสำเนา",
   "working": 0,
   "to_be_repaired": 0,
   "to_be_removed": 0,
   "total": 0
  },
  {
   "code": 21005,
   "type": "ครุภัณฑ์สำนักงาน โรงเรียน",
   "name": "เครื่องพิมพ์ดีด",
   "working": 35,
   "to_be_repaired": 10,
   "to_be_removed": 10,
   "total": 55
  },
  {
   "code": 21006,
   "type": "ครุภัณฑ์สำนักงาน โรงเรียน",
   "name": "ตู้นิรภัย",
   "working": 1,
   "to_be_repaired": 0,
   "to_be_removed": 0,
   "total": 1
  },
  {
   "code": 21007,
   "type": "ครุภัณฑ์สำนักงาน โรงเรียน",
   "name": "เครื่องไมโครคอมพิวเตอร์",
   "working": 108,
   "to_be_repaired": 0,
   "to_be_removed": 0,
   "total": 108
  },
  {
   "code": 21008,
   "type": "ครุภัณฑ์สำนักงาน โรงเรียน",
   "name": "เครื่องพิมพ์ (Printer)",
   "working": 98,
   "to_be_repaired": 0,
   "to_be_removed": 0,
   "total": 98
  },
  {
   "code": 21009,
   "type": "ครุภัณฑ์สำนักงาน โรงเรียน",
   "name": "เครื่องเจาะกระดาษและเข้าเล่ม",
   "working": 0,
   "to_be_repaired": 0,
   "to_be_removed": 0,
   "total": 0
  },
  {
   "code": 21010,
   "type": "ครุภัณฑ์สำนักงาน โรงเรียน",
   "name": "เครื่องถ่ายภาพนิ่งระบบดิจิตอล",
   "working": 0,
   "to_be_repaired": 0,
   "to_be_removed": 0,
   "total": 0
  },
  {
   "code": 21011,
   "type": "ครุภัณฑ์สำนักงาน/โรงเรียน",
   "name": "คอมพิวเตอร์พกพา(Tablet)(ใช้บริหารจัดการ)",
   "working": 0,
   "to_be_repaired": 0,
   "to_be_removed": 0,
   "total": 0
  },
  {
   "code": 21012,
   "type": "ครุภัณฑ์สำนักงาน/โรงเรียน",
   "name": "เครื่องคอมพิวเตอร์พกพา(Notebook)(ใช้บริหารจัดการ)",
   "working": 7,
   "to_be_repaired": 0,
   "to_be_removed": 0,
   "total": 7
  },
  {
   "code": 21013,
   "type": "ครุภัณฑ์สำนักงาน/โรงเรียน",
   "name": "กล้องถ่ายภาพดิจิตอล",
   "working": 5,
   "to_be_repaired": 0,
   "to_be_removed": 0,
   "total": 5
  },
  {
   "code": 22001,
   "type": "ครุภัณฑ์การศึกษา",
   "name": "โต๊ะเก้าอี้นักเรียน ประถมศึกษา",
   "working": 0,
   "to_be_repaired": 0,
   "to_be_removed": 0,
   "total": 0
  },
  {
   "code": 22002,
   "type": "ครุภัณฑ์การศึกษา",
   "name": "โต๊ะเก้าอี้นักเรียน มัธยมศึกษา",
   "working": 1600,
   "to_be_repaired": 0,
   "to_be_removed": 0,
   "total": 1600
  },
  {
   "code": 22003,
   "type": "ครุภัณฑ์การศึกษา",
   "name": "ครุภัณฑ์การสอนวิทยาศาสตร์ ประถมศึกษา",
   "working": 0,
   "to_be_repaired": 0,
   "to_be_removed": 0,
   "total": 0
  },
  {
   "code": 22004,
   "type": "ครุภัณฑ์การศึกษา",
   "name": "ครุภัณฑ์อุปกรณ์วิทยาศาสตร์ ม.ต้น",
   "working": 0,
   "to_be_repaired": 0,
   "to_be_removed": 0,
   "total": 0
  },
  {
   "code": 22005,
   "type": "ครุภัณฑ์การศึกษา",
   "name": "ครุภัณฑ์วิทยาศาสตร์ ม.ปลาย",
   "working": 0,
   "to_be_repaired": 0,
   "to_be_removed": 0,
   "total": 0
  },
  {
   "code": 22006,
   "type": "ครุภัณฑ์การศึกษา",
   "name": "หุ่นจำลองแสดงอวัยวะภายในมนุษย์",
   "working": 0,
   "to_be_repaired": 0,
   "to_be_removed": 0,
   "total": 0
  },
  {
   "code": 22007,
   "type": "ครุภัณฑ์การศึกษา",
   "name": "ครุภัณฑ์ไฟฟ้า",
   "working": 0,
   "to_be_repaired": 0,
   "to_be_removed": 0,
   "total": 0
  },
  {
   "code": 22008,
   "type": "ครุภัณฑ์การศึกษา",
   "name": "ครุภัณฑ์งานอาหารและโภชนาการ",
   "working": 0,
   "to_be_repaired": 0,
   "to_be_removed": 0,
   "total": 0
  },
  {
   "code": 22009,
   "type": "ครุภัณฑ์การศึกษา",
   "name": "ครุภัณฑ์งานผ้าและการตัดเย็บ",
   "working": 0,
   "to_be_repaired": 0,
   "to_be_removed": 0,
   "total": 0
  },
  {
   "code": 22010,
   "type": "ครุภัณฑ์การศึกษา",
   "name": "ครุภัณฑ์โรงฝึกงาน",
   "working": 0,
   "to_be_repaired": 0,
   "to_be_removed": 0,
   "total": 0
  },
  {
   "code": 22011,
   "type": "ครุภัณฑ์การศึกษา",
   "name": "ครุภัณฑ์งานไม้",
   "working": 0,
   "to_be_repaired": 0,
   "to_be_removed": 0,
   "total": 0
  },
  {
   "code": 22012,
   "type": "ครุภัณฑ์การศึกษา",
   "name": "ครุภัณฑ์งานโลหะ",
   "working": 0,
   "to_be_repaired": 0,
   "to_be_removed": 0,
   "total": 0
  },
  {
   "code": 22013,
   "type": "ครุภัณฑ์การศึกษา",
   "name": "ครุภัณฑ์ชางอุตสาหกรรม",
   "working": 0,
   "to_be_repaired": 0,
   "to_be_removed": 0,
   "total": 0
  },
  {
   "code": 22014,
   "type": "ครุภัณฑ์การศึกษา",
   "name": "ครุภัณฑ์งานยนต์",
   "working": 0,
   "to_be_repaired": 0,
   "to_be_removed": 0,
   "total": 0
  },
  {
   "code": 22015,
   "type": "ครุภัณฑ์การศึกษา",
   "name": "ครุภัณฑ์วิชาคหกรรม",
   "working": 0,
   "to_be_repaired": 0,
   "to_be_removed": 0,
   "total": 0
  },
  {
   "code": 22016,
   "type": "ครุภัณฑ์การศึกษา",
   "name": "ครุภัณฑ์วิชาศิลปกรรม",
   "working": 0,
   "to_be_repaired": 0,
   "to_be_removed": 0,
   "total": 0
  },
  {
   "code": 22017,
   "type": "ครุภัณฑ์การศึกษา",
   "name": "ครุภัณฑ์ห้องปฏิบัติการเพาะเห็ด",
   "working": 0,
   "to_be_repaired": 0,
   "to_be_removed": 0,
   "total": 0
  },
  {
   "code": 22018,
   "type": "ครุภัณฑ์การศึกษา",
   "name": "ฃุดอุปกรณ์วิชาชีพเกษตรกรรม",
   "working": 0,
   "to_be_repaired": 0,
   "to_be_removed": 0,
   "total": 0
  },
  {
   "code": 22019,
   "type": "ครุภัณฑ์การศึกษา",
   "name": "ครุภัณฑ์งานเขียนแบบ ม.ต้น",
   "working": 0,
   "to_be_repaired": 0,
   "to_be_removed": 0,
   "total": 0
  },
  {
   "code": 22020,
   "type": "ครุภัณฑ์การศึกษา",
   "name": "เครื่องดนตรีสากล",
   "working": 50,
   "to_be_repaired": 0,
   "to_be_removed": 0,
   "total": 50
  },
  {
   "code": 22021,
   "type": "ครุภัณฑ์การศึกษา",
   "name": "เครื่องดนตรีไทย ชุดเล็ก ประถมศึกษา",
   "working": 0,
   "to_be_repaired": 0,
   "to_be_removed": 0,
   "total": 0
  },
  {
   "code": 22022,
   "type": "ครุภัณฑ์การศึกษา",
   "name": "เครื่องดนตรีไทย ชุดใหญ่ มัธยมศึกษา",
   "working": 54,
   "to_be_repaired": 0,
   "to_be_removed": 0,
   "total": 54
  },
  {
   "code": 22023,
   "type": "ครุภัณฑ์การศึกษา",
   "name": "ชุดอุปกรณ์วิชาพลานามัย",
   "working": 30,
   "to_be_repaired": 0,
   "to_be_removed": 0,
   "total": 30
  },
  {
   "code": 22024,
   "type": "ครุภัณฑ์การศึกษา",
   "name": "โต๊ะเทเบิลเทนนิส",
   "working": 2,
   "to_be_repaired": 0,
   "to_be_removed": 0,
   "total": 2
  },
  {
   "code": 22025,
   "type": "ครุภัณฑ์การศึกษา",
   "name": "ชุดอุปกรณ์เปตอง",
   "working": 0,
   "to_be_repaired": 0,
   "to_be_removed": 0,
   "total": 0
  },
  {
   "code": 22026,
   "type": "ครุภัณฑ์การศึกษา",
   "name": "โทรทัศน์สี",
   "working": 4,
   "to_be_repaired": 0,
   "to_be_removed": 0,
   "total": 4
  },
  {
   "code": 22027,
   "type": "ครุภัณฑ์การศึกษา",
   "name": "วิทยุ - เทป - ซีดี",
   "working": 0,
   "to_be_repaired": 0,
   "to_be_removed": 0,
   "total": 0
  },
  {
   "code": 22028,
   "type": "ครุภัณฑ์การศึกษา",
   "name": "เครื่องเล่น ดีวีดี",
   "working": 1,
   "to_be_repaired": 2,
   "to_be_removed": 0,
   "total": 3
  },
  {
   "code": 22029,
   "type": "ครุภัณฑ์การศึกษา",
   "name": "จานรับสัญญาณดาวเทียม",
   "working": 1,
   "to_be_repaired": 0,
   "to_be_removed": 0,
   "total": 1
  },
  {
   "code": 22030,
   "type": "ครุภัณฑ์การศึกษา",
   "name": "ครุภัณฑ์ห้องสมุด ชุดเล็ก ประถมศึกษา",
   "working": 0,
   "to_be_repaired": 0,
   "to_be_removed": 0,
   "total": 0
  },
  {
   "code": 22031,
   "type": "ครุภัณฑ์การศึกษา",
   "name": "ครุภัณฑ์ห้องสมุด ชุดใหญ่ มัธยมศึกษา",
   "working": 201,
   "to_be_repaired": 0,
   "to_be_removed": 0,
   "total": 201
  },
  {
   "code": 22032,
   "type": "ครุภัณฑ์การศึกษา",
   "name": "เครื่องมัลติมีเดียโปรเจคเตอร์ LCD",
   "working": 4,
   "to_be_repaired": 5,
   "to_be_removed": 0,
   "total": 9
  },
  {
   "code": 22033,
   "type": "ครุภัณฑ์การศึกษา",
   "name": "เครื่องไมโครคอมพิวเตอร์",
   "working": 221,
   "to_be_repaired": 0,
   "to_be_removed": 0,
   "total": 221
  },
  {
   "code": 22034,
   "type": "ครุภัณฑ์การศึกษา",
   "name": "เครื่องพิมพ์ (Printer)",
   "working": 5,
   "to_be_repaired": 0,
   "to_be_removed": 0,
   "total": 5
  },
  {
   "code": 22035,
   "type": "ครุภัณฑ์การศึกษา",
   "name": "อุปกรณ์ห้องสมุดรร.ระดับประถมศึกษา-มัธยมศึกษา",
   "working": 25,
   "to_be_repaired": 0,
   "to_be_removed": 0,
   "total": 25
  },
  {
   "code": 22036,
   "type": "ครุภัณฑ์การศึกษา",
   "name": "ครุภัณฑ์พัฒนาทักษะคิดวิเคราะห์ระดับก่อนประถมศึกษา",
   "working": 0,
   "to_be_repaired": 0,
   "to_be_removed": 0,
   "total": 0
  },
  {
   "code": 22037,
   "type": "ครุภัณฑ์การศึกษา",
   "name": "ครุภัณฑ์พัฒนาทักษะคิดวิเคราะห์ระดับประถมศึกษา",
   "working": 0,
   "to_be_repaired": 0,
   "to_be_removed": 0,
   "total": 0
  },
  {
   "code": 22038,
   "type": "ครุภัณฑ์การศึกษา",
   "name": "อุปกรณ์ศูนย์การเรียนรร.ขนาดเล็ก",
   "working": 0,
   "to_be_repaired": 0,
   "to_be_removed": 0,
   "total": 0
  },
  {
   "code": 22039,
   "type": "ครุภัณฑ์การศึกษา",
   "name": "อุปกรณ์ห้องปฏิบัติการวิทยาศาสตร์ (ประถม-มัธยมต้น)",
   "working": 0,
   "to_be_repaired": 0,
   "to_be_removed": 0,
   "total": 0
  },
  {
   "code": 22040,
   "type": "ครุภัณฑ์การศึกษา",
   "name": "อุปกรณ์ห้องปฏิบัติการวิทยาศาสตร์ (มัธยมศึกษา)",
   "working": 0,
   "to_be_repaired": 0,
   "to_be_removed": 0,
   "total": 0
  },
  {
   "code": 22041,
   "type": "ครุภัณฑ์การศึกษา",
   "name": "คอมพิวเตอร์พกพา(Tablet)",
   "working": 300,
   "to_be_repaired": 1,
   "to_be_removed": 0,
   "total": 301
  },
  {
   "code": 22042,
   "type": "ครุภัณฑ์การศึกษา",
   "name": "เครื่องคอมพิวเตอร์พกพา(Notebook)(ใช้ในการเรียนการสอน)",
   "working": 7,
   "to_be_repaired": 0,
   "to_be_removed": 0,
   "total": 7
  },
  {
   "code": 22043,
   "type": "ครุภัณฑ์การศึกษา",
   "name": "โทรทัศน์สีชนิด จอแบน (LCD)",
   "working": 5,
   "to_be_repaired": 0,
   "to_be_removed": 0,
   "total": 5
  },
  {
   "code": 23001,
   "type": "ครุภัณฑ์ไฟฟ้าและวิทยุ",
   "name": "เครื่องกำเนิดไฟฟ้าพลังแสงอาทิตย์ เบนซิน",
   "working": 0,
   "to_be_repaired": 0,
   "to_be_removed": 0,
   "total": 0
  },
  {
   "code": 23002,
   "type": "ครุภัณฑ์ไฟฟ้าและวิทยุ",
   "name": "เครื่องตัดกระแสไฟฟ้า",
   "working": 0,
   "to_be_repaired": 0,
   "to_be_removed": 0,
   "total": 0
  },
  {
   "code": 23003,
   "type": "ครุภัณฑ์ไฟฟ้าและวิทยุ",
   "name": "เครื่องขยายเสียง",
   "working": 22,
   "to_be_repaired": 5,
   "to_be_removed": 0,
   "total": 27
  },
  {
   "code": 23004,
   "type": "ครุภัณฑ์ไฟฟ้าและวิทยุ",
   "name": "เครื่องกำเนิดไฟฟ้า 5, 10 กิโลวัตต์",
   "working": 0,
   "to_be_repaired": 0,
   "to_be_removed": 0,
   "total": 0
  },
  {
   "code": 23005,
   "type": "ครุภัณฑ์ไฟฟ้าและวิทยุ",
   "name": "เครื่องปรับอากาศ",
   "working": 90,
   "to_be_repaired": 0,
   "to_be_removed": 0,
   "total": 90
  },
  {
   "code": 24001,
   "type": "ครุภัณฑ์งานบ้านและงานครัว",
   "name": "เครื่องกรองน้ำ",
   "working": 13,
   "to_be_repaired": 0,
   "to_be_removed": 0,
   "total": 13
  },
  {
   "code": 24002,
   "type": "ครุภัณฑ์งานบ้านและงานครัว",
   "name": "เครื่องทำน้ำเย็น",
   "working": 10,
   "to_be_repaired": 0,
   "to_be_removed": 0,
   "total": 10
  },
  {
   "code": 24003,
   "type": "ครุภัณฑ์งานบ้านและงานครัว",
   "name": "ถังน้ำขนาด 2000 ลิตร แบบไฟเบอร์กลาส",
   "working": 0,
   "to_be_repaired": 0,
   "to_be_removed": 0,
   "total": 0
  },
  {
   "code": 24004,
   "type": "ครุภัณฑ์งานบ้านและงานครัว",
   "name": "เครื่องตัดหญ้า",
   "working": 0,
   "to_be_repaired": 0,
   "to_be_removed": 0,
   "total": 0
  },
  {
   "code": 24005,
   "type": "ครุภัณฑ์งานบ้านและงานครัว",
   "name": "โต๊ะอาหารพร้อมเก้าอี้",
   "working": 0,
   "to_be_repaired": 0,
   "to_be_removed": 0,
   "total": 0
  },
  {
   "code": 24006,
   "type": "ครุภัณฑ์งานบ้านและงานครัว",
   "name": "ตู้เย็น",
   "working": 6,
   "to_be_repaired": 0,
   "to_be_removed": 0,
   "total": 6
  },
  {
   "code": 24007,
   "type": "ครุภัณฑ์งานบ้านและงานครัว",
   "name": "ถังน้ำขนาด 2000 ลิดร แบบพลาสติก",
   "working": 0,
   "to_be_repaired": 0,
   "to_be_removed": 0,
   "total": 0
  },
  {
   "code": 24008,
   "type": "ครุภัณฑ์งานบ้านและงานครัว",
   "name": "ถังน้ำขนาด 1000 ลิตร ขึ้นไป แบบไฟเบอร์กลาส",
   "working": 0,
   "to_be_repaired": 0,
   "to_be_removed": 0,
   "total": 0
  },
  {
   "code": 24009,
   "type": "ครุภัณฑ์งานบ้านและงานครัว",
   "name": "ถังน้ำขนาด 1000 ลิตร ขึ้นไป แบบพลาสติก",
   "working": 0,
   "to_be_repaired": 0,
   "to_be_removed": 0,
   "total": 0
  },
  {
   "code": 24010,
   "type": "ครุภัณฑ์งานบ้านและงานครัว",
   "name": "ถังน้ำขนาด 1000 ลิตร ขึ้นไป แบบสแตนเลส",
   "working": 3,
   "to_be_repaired": 0,
   "to_be_removed": 0,
   "total": 3
  },
  {
   "code": 25001,
   "type": "ครุภัณฑ์ยานพาหนะ",
   "name": "รถโดยสาร 12 ที่นั่ง",
   "working": 0,
   "to_be_repaired": 0,
   "to_be_removed": 0,
   "total": 0
  },
  {
   "code": 25002,
   "type": "ครุภัณฑ์ยานพาหนะ",
   "name": "รถกระบะ",
   "working": 1,
   "to_be_repaired": 0,
   "to_be_removed": 0,
   "total": 1
  }
 ],
 "tables": {
  "working": 1600,
  "to_be_repaired": 0,
  "to_be_removed": 0,
  "total": 1600
 },
 "durable_goods_stats": {
  "working": 2920,
  "to_be_repaired": 23,
  "to_be_removed": 10,
  "total": 2953
 },
 "internet": {
  "provider": "-",
  "type": "-",
  "speed": "-",
  "status": "-",
  "monthly_price": "-",
  "lan_network": "มีระบบเครือข่าย LAN",
  "wireless_lan_network": "มีระบบเครือข่ายไร้สาย (Wireless LAN)"
 },
 "staff": {
  "men": 29,
  "women": 25,
  "total": 54,
  "ผู้อำนวยการ": {
   "men": 0,
   "women": 1,
   "total": 1,
   "คศ1": {
    "men": 0,
    "women": 0,
    "total": 0
   },
   "คศ2": {
    "men": 0,
    "women": 1,
    "total": 1
   },
   "คศ3": {
    "men": 0,
    "women": 0,
    "total": 0
   },
   "คศ4": {
    "men": 0,
    "women": 0,
    "total": 0
   },
   "คศ5": {
    "men": 0,
    "women": 0,
    "total": 0
   }
  },
  "รองผู้อำนวยการ": {
   "men": 1,
   "women": 0,
   "total": 1,
   "คศ1": {
    "men": 0,
    "women": 0,
    "total": 0
   },
   "คศ2": {
    "men": 1,
    "women": 0,
    "total": 1
   },
   "คศ3": {
    "men": 0,
    "women": 0,
    "total": 0
   },
   "คศ4": {
    "men": 0,
    "women": 0,
    "total": 0
   }
  },
  "ครู": {
   "men": 16,
   "women": 18,
   "total": 34,
   "ครูผู้ช่วย": {
    "men": 0,
    "women": 0,
    "total": 0
   },
   "คศ1": {
    "men": 13,
    "women": 12,
    "total": 25
   },
   "คศ2": {
    "men": 1,
    "women": 5,
    "total": 6
   },
   "คศ3": {
    "men": 2,
    "women": 1,
    "total": 3
   },
   "คศ4": {
    "men": 0,
    "women": 0,
    "total": 0
   },
   "คศ5": {
    "men": 0,
    "women": 0,
    "total": 0
   }
  },
  "พนักงาน": {
   "men": 12,
   "women": 6,
   "total": 18,
   "ลูกจ้างประจำ": {
    "men": 3,
    "women": 0,
    "total": 3
   },
   "พนักงานราชการ": {
    "men": 0,
    "women": 0,
    "total": 0
   },
   "ลูกจ้างชั่วคราว": {
    "men": 9,
    "women": 6,
    "total": 15
   }
  }
 },
 "student": {
  "total": {
   "อ": 0,
   "ป": 0,
   "มต": 221,
   "มป": 243,
   "ม": 464,
   "all": 464
  },
  "อ1": {
   "men": 0,
   "women": 0,
   "total": 0,
   "class": 0
  },
  "อ2": {
   "men": 0,
   "women": 0,
   "total": 0,
   "class": 0
  },
  "อ3": {
   "men": 0,
   "women": 0,
   "total": 0,
   "class": 0
  },
  "ป1": {
   "men": 0,
   "women": 0,
   "total": 0,
   "class": 0
  },
  "ป2": {
   "men": 0,
   "women": 0,
   "total": 0,
   "class": 0
  },
  "ป3": {
   "men": 0,
   "women": 0,
   "total": 0,
   "class": 0
  },
  "ป4": {
   "men": 0,
   "women": 0,
   "total": 0,
   "class": 0
  },
  "ป5": {
   "men": 0,
   "women": 0,
   "total": 0,
   "class": 0
  },
  "ป6": {
   "men": 0,
   "women": 0,
   "total": 0,
   "class": 0
  },
  "ม1": {
   "men": 46,
   "women": 35,
   "total": 81,
   "class": 3
  },
  "ม2": {
   "men": 35,
   "women": 27,
   "total": 62,
   "class": 4
  },
  "ม3": {
   "men": 34,
   "women": 44,
   "total": 78,
   "class": 4
  },
  "ม4": {
   "men": 40,
   "women": 32,
   "total": 72,
   "class": 7
  },
  "ม5": {
   "men": 44,
   "women": 31,
   "total": 75,
   "class": 7
  },
  "ม6": {
   "men": 46,
   "women": 50,
   "total": 96,
   "class": 7
  },
  "ปวช1": {
   "men": 0,
   "women": 0,
   "total": 0,
   "class": 0
  },
  "ปวช2": {
   "men": 0,
   "women": 0,
   "total": 0,
   "class": 0
  },
  "ปวช3": {
   "men": 0,
   "women": 0,
   "total": 0,
   "class": 0
  }
 }
}